{"nodes": [{"id": "dashboard", "label": "dashboard.js", "file_type": "code", "source_file": "packages\\flowwatch\\src\\dashboard\\static\\dashboard.js", "source_location": "L1"}, {"id": "dashboard_pinnedworkflownames", "label": "pinnedWorkflowNames()", "file_type": "code", "source_file": "packages\\flowwatch\\src\\dashboard\\static\\dashboard.js", "source_location": "L45"}, {"id": "dashboard_savepinnedworkflownames", "label": "savePinnedWorkflowNames()", "file_type": "code", "source_file": "packages\\flowwatch\\src\\dashboard\\static\\dashboard.js", "source_location": "L54"}, {"id": "dashboard_dashboardbasepath", "label": "dashboardBasePath()", "file_type": "code", "source_file": "packages\\flowwatch\\src\\dashboard\\static\\dashboard.js", "source_location": "L63"}, {"id": "dashboard_apipath", "label": "apiPath()", "file_type": "code", "source_file": "packages\\flowwatch\\src\\dashboard\\static\\dashboard.js", "source_location": "L73"}, {"id": "dashboard_escapehtml", "label": "escapeHtml()", "file_type": "code", "source_file": "packages\\flowwatch\\src\\dashboard\\static\\dashboard.js", "source_location": "L77"}, {"id": "dashboard_apirequest", "label": "apiRequest()", "file_type": "code", "source_file": "packages\\flowwatch\\src\\dashboard\\static\\dashboard.js", "source_location": "L86"}, {"id": "dashboard_normalizeworkflow", "label": "normalizeWorkflow()", "file_type": "code", "source_file": "packages\\flowwatch\\src\\dashboard\\static\\dashboard.js", "source_location": "L121"}, {"id": "dashboard_normalizeexecution", "label": "normalizeExecution()", "file_type": "code", "source_file": "packages\\flowwatch\\src\\dashboard\\static\\dashboard.js", "source_location": "L141"}, {"id": "dashboard_normalizeflag", "label": "normalizeFlag()", "file_type": "code", "source_file": "packages\\flowwatch\\src\\dashboard\\static\\dashboard.js", "source_location": "L154"}, {"id": "dashboard_normalizeerror", "label": "normalizeError()", "file_type": "code", "source_file": "packages\\flowwatch\\src\\dashboard\\static\\dashboard.js", "source_location": "L163"}, {"id": "dashboard_normalizetrace", "label": "normalizeTrace()", "file_type": "code", "source_file": "packages\\flowwatch\\src\\dashboard\\static\\dashboard.js", "source_location": "L173"}, {"id": "dashboard_formattime", "label": "formatTime()", "file_type": "code", "source_file": "packages\\flowwatch\\src\\dashboard\\static\\dashboard.js", "source_location": "L182"}, {"id": "dashboard_formatdatetime", "label": "formatDateTime()", "file_type": "code", "source_file": "packages\\flowwatch\\src\\dashboard\\static\\dashboard.js", "source_location": "L189"}, {"id": "dashboard_formatdurationlabel", "label": "formatDurationLabel()", "file_type": "code", "source_file": "packages\\flowwatch\\src\\dashboard\\static\\dashboard.js", "source_location": "L196"}, {"id": "dashboard_loaddashboarddata", "label": "loadDashboardData()", "file_type": "code", "source_file": "packages\\flowwatch\\src\\dashboard\\static\\dashboard.js", "source_location": "L202"}, {"id": "dashboard_badgeforstatus", "label": "badgeForStatus()", "file_type": "code", "source_file": "packages\\flowwatch\\src\\dashboard\\static\\dashboard.js", "source_location": "L235"}, {"id": "dashboard_graphstatusclass", "label": "graphStatusClass()", "file_type": "code", "source_file": "packages\\flowwatch\\src\\dashboard\\static\\dashboard.js", "source_location": "L242"}, {"id": "dashboard_tableemptyrow", "label": "tableEmptyRow()", "file_type": "code", "source_file": "packages\\flowwatch\\src\\dashboard\\static\\dashboard.js", "source_location": "L249"}, {"id": "dashboard_workflowstepstatus", "label": "workflowStepStatus()", "file_type": "code", "source_file": "packages\\flowwatch\\src\\dashboard\\static\\dashboard.js", "source_location": "L262"}, {"id": "dashboard_badgeformethod", "label": "badgeForMethod()", "file_type": "code", "source_file": "packages\\flowwatch\\src\\dashboard\\static\\dashboard.js", "source_location": "L274"}, {"id": "dashboard_showpage", "label": "showPage()", "file_type": "code", "source_file": "packages\\flowwatch\\src\\dashboard\\static\\dashboard.js", "source_location": "L282"}, {"id": "dashboard_opendrawer", "label": "openDrawer()", "file_type": "code", "source_file": "packages\\flowwatch\\src\\dashboard\\static\\dashboard.js", "source_location": "L298"}, {"id": "dashboard_closedrawer", "label": "closeDrawer()", "file_type": "code", "source_file": "packages\\flowwatch\\src\\dashboard\\static\\dashboard.js", "source_location": "L306"}, {"id": "dashboard_latestexecutionforworkflow", "label": "latestExecutionForWorkflow()", "file_type": "code", "source_file": "packages\\flowwatch\\src\\dashboard\\static\\dashboard.js", "source_location": "L312"}, {"id": "dashboard_allexecutionsforworkflow", "label": "allExecutionsForWorkflow()", "file_type": "code", "source_file": "packages\\flowwatch\\src\\dashboard\\static\\dashboard.js", "source_location": "L317"}, {"id": "dashboard_workflowerrorforstep", "label": "workflowErrorForStep()", "file_type": "code", "source_file": "packages\\flowwatch\\src\\dashboard\\static\\dashboard.js", "source_location": "L321"}, {"id": "dashboard_workflowexecutionsteps", "label": "workflowExecutionSteps()", "file_type": "code", "source_file": "packages\\flowwatch\\src\\dashboard\\static\\dashboard.js", "source_location": "L351"}, {"id": "dashboard_badgeforstepstatus", "label": "badgeForStepStatus()", "file_type": "code", "source_file": "packages\\flowwatch\\src\\dashboard\\static\\dashboard.js", "source_location": "L383"}, {"id": "dashboard_workflowsteperrordetail", "label": "workflowStepErrorDetail()", "file_type": "code", "source_file": "packages\\flowwatch\\src\\dashboard\\static\\dashboard.js", "source_location": "L389"}, {"id": "dashboard_renderoverview", "label": "renderOverview()", "file_type": "code", "source_file": "packages\\flowwatch\\src\\dashboard\\static\\dashboard.js", "source_location": "L404"}, {"id": "dashboard_renderworkflows", "label": "renderWorkflows()", "file_type": "code", "source_file": "packages\\flowwatch\\src\\dashboard\\static\\dashboard.js", "source_location": "L495"}, {"id": "dashboard_getworkflowstepclass", "label": "getWorkflowStepClass()", "file_type": "code", "source_file": "packages\\flowwatch\\src\\dashboard\\static\\dashboard.js", "source_location": "L536"}, {"id": "dashboard_getworkflowarrowclass", "label": "getWorkflowArrowClass()", "file_type": "code", "source_file": "packages\\flowwatch\\src\\dashboard\\static\\dashboard.js", "source_location": "L545"}, {"id": "dashboard_renderexecutions", "label": "renderExecutions()", "file_type": "code", "source_file": "packages\\flowwatch\\src\\dashboard\\static\\dashboard.js", "source_location": "L554"}, {"id": "dashboard_renderflags", "label": "renderFlags()", "file_type": "code", "source_file": "packages\\flowwatch\\src\\dashboard\\static\\dashboard.js", "source_location": "L576"}, {"id": "dashboard_rendererrors", "label": "renderErrors()", "file_type": "code", "source_file": "packages\\flowwatch\\src\\dashboard\\static\\dashboard.js", "source_location": "L592"}, {"id": "dashboard_rendertraces", "label": "renderTraces()", "file_type": "code", "source_file": "packages\\flowwatch\\src\\dashboard\\static\\dashboard.js", "source_location": "L615"}, {"id": "dashboard_rendertracegraph", "label": "renderTraceGraph()", "file_type": "code", "source_file": "packages\\flowwatch\\src\\dashboard\\static\\dashboard.js", "source_location": "L652"}, {"id": "dashboard_renderglobalsearch", "label": "renderGlobalSearch()", "file_type": "code", "source_file": "packages\\flowwatch\\src\\dashboard\\static\\dashboard.js", "source_location": "L780"}, {"id": "dashboard_renderhealth", "label": "renderHealth()", "file_type": "code", "source_file": "packages\\flowwatch\\src\\dashboard\\static\\dashboard.js", "source_location": "L868"}, {"id": "dashboard_rendersettings", "label": "renderSettings()", "file_type": "code", "source_file": "packages\\flowwatch\\src\\dashboard\\static\\dashboard.js", "source_location": "L901"}, {"id": "dashboard_savesetting", "label": "saveSetting()", "file_type": "code", "source_file": "packages\\flowwatch\\src\\dashboard\\static\\dashboard.js", "source_location": "L932"}, {"id": "dashboard_togglesetting", "label": "toggleSetting()", "file_type": "code", "source_file": "packages\\flowwatch\\src\\dashboard\\static\\dashboard.js", "source_location": "L962"}, {"id": "dashboard_savegroqapikey", "label": "saveGroqApiKey()", "file_type": "code", "source_file": "packages\\flowwatch\\src\\dashboard\\static\\dashboard.js", "source_location": "L990"}, {"id": "dashboard_loadsavedgroqcredentials", "label": "loadSavedGroqCredentials()", "file_type": "code", "source_file": "packages\\flowwatch\\src\\dashboard\\static\\dashboard.js", "source_location": "L1029"}, {"id": "dashboard_selectedgroqmodel", "label": "selectedGroqModel()", "file_type": "code", "source_file": "packages\\flowwatch\\src\\dashboard\\static\\dashboard.js", "source_location": "L1045"}, {"id": "dashboard_groqmodeloptions", "label": "groqModelOptions()", "file_type": "code", "source_file": "packages\\flowwatch\\src\\dashboard\\static\\dashboard.js", "source_location": "L1049"}, {"id": "dashboard_rendergroqmodelcontrols", "label": "renderGroqModelControls()", "file_type": "code", "source_file": "packages\\flowwatch\\src\\dashboard\\static\\dashboard.js", "source_location": "L1058"}, {"id": "dashboard_renderaiplaceholders", "label": "renderAiPlaceholders()", "file_type": "code", "source_file": "packages\\flowwatch\\src\\dashboard\\static\\dashboard.js", "source_location": "L1069"}, {"id": "dashboard_loadaiinsights", "label": "loadAiInsights()", "file_type": "code", "source_file": "packages\\flowwatch\\src\\dashboard\\static\\dashboard.js", "source_location": "L1151"}, {"id": "dashboard_loadgroqmodelsforsettings", "label": "loadGroqModelsForSettings()", "file_type": "code", "source_file": "packages\\flowwatch\\src\\dashboard\\static\\dashboard.js", "source_location": "L1175"}, {"id": "dashboard_initaichat", "label": "initAiChat()", "file_type": "code", "source_file": "packages\\flowwatch\\src\\dashboard\\static\\dashboard.js", "source_location": "L1190"}, {"id": "dashboard_savemessages", "label": "saveMessages()", "file_type": "code", "source_file": "packages\\flowwatch\\src\\dashboard\\static\\dashboard.js", "source_location": "L1195"}, {"id": "dashboard_clearaichat", "label": "clearAiChat()", "file_type": "code", "source_file": "packages\\flowwatch\\src\\dashboard\\static\\dashboard.js", "source_location": "L1199"}, {"id": "dashboard_rendermessages", "label": "renderMessages()", "file_type": "code", "source_file": "packages\\flowwatch\\src\\dashboard\\static\\dashboard.js", "source_location": "L1205"}, {"id": "dashboard_formatmessagemarkdown", "label": "formatMessageMarkdown()", "file_type": "code", "source_file": "packages\\flowwatch\\src\\dashboard\\static\\dashboard.js", "source_location": "L1239"}, {"id": "dashboard_sendmessage", "label": "sendMessage()", "file_type": "code", "source_file": "packages\\flowwatch\\src\\dashboard\\static\\dashboard.js", "source_location": "L1328"}, {"id": "dashboard_renderall", "label": "renderAll()", "file_type": "code", "source_file": "packages\\flowwatch\\src\\dashboard\\static\\dashboard.js", "source_location": "L1384"}, {"id": "dashboard_workflowdetail", "label": "workflowDetail()", "file_type": "code", "source_file": "packages\\flowwatch\\src\\dashboard\\static\\dashboard.js", "source_location": "L1396"}, {"id": "dashboard_executiondetail", "label": "executionDetail()", "file_type": "code", "source_file": "packages\\flowwatch\\src\\dashboard\\static\\dashboard.js", "source_location": "L1460"}, {"id": "dashboard_errordetail", "label": "errorDetail()", "file_type": "code", "source_file": "packages\\flowwatch\\src\\dashboard\\static\\dashboard.js", "source_location": "L1501"}, {"id": "dashboard_tracedetail", "label": "traceDetail()", "file_type": "code", "source_file": "packages\\flowwatch\\src\\dashboard\\static\\dashboard.js", "source_location": "L1517"}, {"id": "dashboard_syncui", "label": "syncUI()", "file_type": "code", "source_file": "packages\\flowwatch\\src\\dashboard\\static\\dashboard.js", "source_location": "L1852"}], "edges": [{"source": "dashboard", "target": "dashboard_pinnedworkflownames", "relation": "contains", "confidence": "EXTRACTED", "source_file": "packages\\flowwatch\\src\\dashboard\\static\\dashboard.js", "source_location": "L45", "weight": 1.0}, {"source": "dashboard", "target": "dashboard_savepinnedworkflownames", "relation": "contains", "confidence": "EXTRACTED", "source_file": "packages\\flowwatch\\src\\dashboard\\static\\dashboard.js", "source_location": "L54", "weight": 1.0}, {"source": "dashboard", "target": "dashboard_dashboardbasepath", "relation": "contains", "confidence": "EXTRACTED", "source_file": "packages\\flowwatch\\src\\dashboard\\static\\dashboard.js", "source_location": "L63", "weight": 1.0}, {"source": "dashboard", "target": "dashboard_apipath", "relation": "contains", "confidence": "EXTRACTED", "source_file": "packages\\flowwatch\\src\\dashboard\\static\\dashboard.js", "source_location": "L73", "weight": 1.0}, {"source": "dashboard", "target": "dashboard_escapehtml", "relation": "contains", "confidence": "EXTRACTED", "source_file": "packages\\flowwatch\\src\\dashboard\\static\\dashboard.js", "source_location": "L77", "weight": 1.0}, {"source": "dashboard", "target": "dashboard_apirequest", "relation": "contains", "confidence": "EXTRACTED", "source_file": "packages\\flowwatch\\src\\dashboard\\static\\dashboard.js", "source_location": "L86", "weight": 1.0}, {"source": "dashboard", "target": "dashboard_normalizeworkflow", "relation": "contains", "confidence": "EXTRACTED", "source_file": "packages\\flowwatch\\src\\dashboard\\static\\dashboard.js", "source_location": "L121", "weight": 1.0}, {"source": "dashboard", "target": "dashboard_normalizeexecution", "relation": "contains", "confidence": "EXTRACTED", "source_file": "packages\\flowwatch\\src\\dashboard\\static\\dashboard.js", "source_location": "L141", "weight": 1.0}, {"source": "dashboard", "target": "dashboard_normalizeflag", "relation": "contains", "confidence": "EXTRACTED", "source_file": "packages\\flowwatch\\src\\dashboard\\static\\dashboard.js", "source_location": "L154", "weight": 1.0}, {"source": "dashboard", "target": "dashboard_normalizeerror", "relation": "contains", "confidence": "EXTRACTED", "source_file": "packages\\flowwatch\\src\\dashboard\\static\\dashboard.js", "source_location": "L163", "weight": 1.0}, {"source": "dashboard", "target": "dashboard_normalizetrace", "relation": "contains", "confidence": "EXTRACTED", "source_file": "packages\\flowwatch\\src\\dashboard\\static\\dashboard.js", "source_location": "L173", "weight": 1.0}, {"source": "dashboard", "target": "dashboard_formattime", "relation": "contains", "confidence": "EXTRACTED", "source_file": "packages\\flowwatch\\src\\dashboard\\static\\dashboard.js", "source_location": "L182", "weight": 1.0}, {"source": "dashboard", "target": "dashboard_formatdatetime", "relation": "contains", "confidence": "EXTRACTED", "source_file": "packages\\flowwatch\\src\\dashboard\\static\\dashboard.js", "source_location": "L189", "weight": 1.0}, {"source": "dashboard", "target": "dashboard_formatdurationlabel", "relation": "contains", "confidence": "EXTRACTED", "source_file": "packages\\flowwatch\\src\\dashboard\\static\\dashboard.js", "source_location": "L196", "weight": 1.0}, {"source": "dashboard", "target": "dashboard_loaddashboarddata", "relation": "contains", "confidence": "EXTRACTED", "source_file": "packages\\flowwatch\\src\\dashboard\\static\\dashboard.js", "source_location": "L202", "weight": 1.0}, {"source": "dashboard", "target": "dashboard_badgeforstatus", "relation": "contains", "confidence": "EXTRACTED", "source_file": "packages\\flowwatch\\src\\dashboard\\static\\dashboard.js", "source_location": "L235", "weight": 1.0}, {"source": "dashboard", "target": "dashboard_graphstatusclass", "relation": "contains", "confidence": "EXTRACTED", "source_file": "packages\\flowwatch\\src\\dashboard\\static\\dashboard.js", "source_location": "L242", "weight": 1.0}, {"source": "dashboard", "target": "dashboard_tableemptyrow", "relation": "contains", "confidence": "EXTRACTED", "source_file": "packages\\flowwatch\\src\\dashboard\\static\\dashboard.js", "source_location": "L249", "weight": 1.0}, {"source": "dashboard", "target": "dashboard_workflowstepstatus", "relation": "contains", "confidence": "EXTRACTED", "source_file": "packages\\flowwatch\\src\\dashboard\\static\\dashboard.js", "source_location": "L262", "weight": 1.0}, {"source": "dashboard", "target": "dashboard_badgeformethod", "relation": "contains", "confidence": "EXTRACTED", "source_file": "packages\\flowwatch\\src\\dashboard\\static\\dashboard.js", "source_location": "L274", "weight": 1.0}, {"source": "dashboard", "target": "dashboard_showpage", "relation": "contains", "confidence": "EXTRACTED", "source_file": "packages\\flowwatch\\src\\dashboard\\static\\dashboard.js", "source_location": "L282", "weight": 1.0}, {"source": "dashboard", "target": "dashboard_opendrawer", "relation": "contains", "confidence": "EXTRACTED", "source_file": "packages\\flowwatch\\src\\dashboard\\static\\dashboard.js", "source_location": "L298", "weight": 1.0}, {"source": "dashboard", "target": "dashboard_closedrawer", "relation": "contains", "confidence": "EXTRACTED", "source_file": "packages\\flowwatch\\src\\dashboard\\static\\dashboard.js", "source_location": "L306", "weight": 1.0}, {"source": "dashboard", "target": "dashboard_latestexecutionforworkflow", "relation": "contains", "confidence": "EXTRACTED", "source_file": "packages\\flowwatch\\src\\dashboard\\static\\dashboard.js", "source_location": "L312", "weight": 1.0}, {"source": "dashboard", "target": "dashboard_allexecutionsforworkflow", "relation": "contains", "confidence": "EXTRACTED", "source_file": "packages\\flowwatch\\src\\dashboard\\static\\dashboard.js", "source_location": "L317", "weight": 1.0}, {"source": "dashboard", "target": "dashboard_workflowerrorforstep", "relation": "contains", "confidence": "EXTRACTED", "source_file": "packages\\flowwatch\\src\\dashboard\\static\\dashboard.js", "source_location": "L321", "weight": 1.0}, {"source": "dashboard", "target": "dashboard_workflowexecutionsteps", "relation": "contains", "confidence": "EXTRACTED", "source_file": "packages\\flowwatch\\src\\dashboard\\static\\dashboard.js", "source_location": "L351", "weight": 1.0}, {"source": "dashboard", "target": "dashboard_badgeforstepstatus", "relation": "contains", "confidence": "EXTRACTED", "source_file": "packages\\flowwatch\\src\\dashboard\\static\\dashboard.js", "source_location": "L383", "weight": 1.0}, {"source": "dashboard", "target": "dashboard_workflowsteperrordetail", "relation": "contains", "confidence": "EXTRACTED", "source_file": "packages\\flowwatch\\src\\dashboard\\static\\dashboard.js", "source_location": "L389", "weight": 1.0}, {"source": "dashboard", "target": "dashboard_renderoverview", "relation": "contains", "confidence": "EXTRACTED", "source_file": "packages\\flowwatch\\src\\dashboard\\static\\dashboard.js", "source_location": "L404", "weight": 1.0}, {"source": "dashboard", "target": "dashboard_renderworkflows", "relation": "contains", "confidence": "EXTRACTED", "source_file": "packages\\flowwatch\\src\\dashboard\\static\\dashboard.js", "source_location": "L495", "weight": 1.0}, {"source": "dashboard", "target": "dashboard_getworkflowstepclass", "relation": "contains", "confidence": "EXTRACTED", "source_file": "packages\\flowwatch\\src\\dashboard\\static\\dashboard.js", "source_location": "L536", "weight": 1.0}, {"source": "dashboard", "target": "dashboard_getworkflowarrowclass", "relation": "contains", "confidence": "EXTRACTED", "source_file": "packages\\flowwatch\\src\\dashboard\\static\\dashboard.js", "source_location": "L545", "weight": 1.0}, {"source": "dashboard", "target": "dashboard_renderexecutions", "relation": "contains", "confidence": "EXTRACTED", "source_file": "packages\\flowwatch\\src\\dashboard\\static\\dashboard.js", "source_location": "L554", "weight": 1.0}, {"source": "dashboard", "target": "dashboard_renderflags", "relation": "contains", "confidence": "EXTRACTED", "source_file": "packages\\flowwatch\\src\\dashboard\\static\\dashboard.js", "source_location": "L576", "weight": 1.0}, {"source": "dashboard", "target": "dashboard_rendererrors", "relation": "contains", "confidence": "EXTRACTED", "source_file": "packages\\flowwatch\\src\\dashboard\\static\\dashboard.js", "source_location": "L592", "weight": 1.0}, {"source": "dashboard", "target": "dashboard_rendertraces", "relation": "contains", "confidence": "EXTRACTED", "source_file": "packages\\flowwatch\\src\\dashboard\\static\\dashboard.js", "source_location": "L615", "weight": 1.0}, {"source": "dashboard", "target": "dashboard_rendertracegraph", "relation": "contains", "confidence": "EXTRACTED", "source_file": "packages\\flowwatch\\src\\dashboard\\static\\dashboard.js", "source_location": "L652", "weight": 1.0}, {"source": "dashboard", "target": "dashboard_renderglobalsearch", "relation": "contains", "confidence": "EXTRACTED", "source_file": "packages\\flowwatch\\src\\dashboard\\static\\dashboard.js", "source_location": "L780", "weight": 1.0}, {"source": "dashboard", "target": "dashboard_renderhealth", "relation": "contains", "confidence": "EXTRACTED", "source_file": "packages\\flowwatch\\src\\dashboard\\static\\dashboard.js", "source_location": "L868", "weight": 1.0}, {"source": "dashboard", "target": "dashboard_rendersettings", "relation": "contains", "confidence": "EXTRACTED", "source_file": "packages\\flowwatch\\src\\dashboard\\static\\dashboard.js", "source_location": "L901", "weight": 1.0}, {"source": "dashboard", "target": "dashboard_savesetting", "relation": "contains", "confidence": "EXTRACTED", "source_file": "packages\\flowwatch\\src\\dashboard\\static\\dashboard.js", "source_location": "L932", "weight": 1.0}, {"source": "dashboard", "target": "dashboard_togglesetting", "relation": "contains", "confidence": "EXTRACTED", "source_file": "packages\\flowwatch\\src\\dashboard\\static\\dashboard.js", "source_location": "L962", "weight": 1.0}, {"source": "dashboard", "target": "dashboard_savegroqapikey", "relation": "contains", "confidence": "EXTRACTED", "source_file": "packages\\flowwatch\\src\\dashboard\\static\\dashboard.js", "source_location": "L990", "weight": 1.0}, {"source": "dashboard", "target": "dashboard_loadsavedgroqcredentials", "relation": "contains", "confidence": "EXTRACTED", "source_file": "packages\\flowwatch\\src\\dashboard\\static\\dashboard.js", "source_location": "L1029", "weight": 1.0}, {"source": "dashboard", "target": "dashboard_selectedgroqmodel", "relation": "contains", "confidence": "EXTRACTED", "source_file": "packages\\flowwatch\\src\\dashboard\\static\\dashboard.js", "source_location": "L1045", "weight": 1.0}, {"source": "dashboard", "target": "dashboard_groqmodeloptions", "relation": "contains", "confidence": "EXTRACTED", "source_file": "packages\\flowwatch\\src\\dashboard\\static\\dashboard.js", "source_location": "L1049", "weight": 1.0}, {"source": "dashboard", "target": "dashboard_rendergroqmodelcontrols", "relation": "contains", "confidence": "EXTRACTED", "source_file": "packages\\flowwatch\\src\\dashboard\\static\\dashboard.js", "source_location": "L1058", "weight": 1.0}, {"source": "dashboard", "target": "dashboard_renderaiplaceholders", "relation": "contains", "confidence": "EXTRACTED", "source_file": "packages\\flowwatch\\src\\dashboard\\static\\dashboard.js", "source_location": "L1069", "weight": 1.0}, {"source": "dashboard", "target": "dashboard_loadaiinsights", "relation": "contains", "confidence": "EXTRACTED", "source_file": "packages\\flowwatch\\src\\dashboard\\static\\dashboard.js", "source_location": "L1151", "weight": 1.0}, {"source": "dashboard", "target": "dashboard_loadgroqmodelsforsettings", "relation": "contains", "confidence": "EXTRACTED", "source_file": "packages\\flowwatch\\src\\dashboard\\static\\dashboard.js", "source_location": "L1175", "weight": 1.0}, {"source": "dashboard", "target": "dashboard_initaichat", "relation": "contains", "confidence": "EXTRACTED", "source_file": "packages\\flowwatch\\src\\dashboard\\static\\dashboard.js", "source_location": "L1190", "weight": 1.0}, {"source": "dashboard", "target": "dashboard_savemessages", "relation": "contains", "confidence": "EXTRACTED", "source_file": "packages\\flowwatch\\src\\dashboard\\static\\dashboard.js", "source_location": "L1195", "weight": 1.0}, {"source": "dashboard", "target": "dashboard_clearaichat", "relation": "contains", "confidence": "EXTRACTED", "source_file": "packages\\flowwatch\\src\\dashboard\\static\\dashboard.js", "source_location": "L1199", "weight": 1.0}, {"source": "dashboard", "target": "dashboard_rendermessages", "relation": "contains", "confidence": "EXTRACTED", "source_file": "packages\\flowwatch\\src\\dashboard\\static\\dashboard.js", "source_location": "L1205", "weight": 1.0}, {"source": "dashboard", "target": "dashboard_formatmessagemarkdown", "relation": "contains", "confidence": "EXTRACTED", "source_file": "packages\\flowwatch\\src\\dashboard\\static\\dashboard.js", "source_location": "L1239", "weight": 1.0}, {"source": "dashboard", "target": "dashboard_sendmessage", "relation": "contains", "confidence": "EXTRACTED", "source_file": "packages\\flowwatch\\src\\dashboard\\static\\dashboard.js", "source_location": "L1328", "weight": 1.0}, {"source": "dashboard", "target": "dashboard_renderall", "relation": "contains", "confidence": "EXTRACTED", "source_file": "packages\\flowwatch\\src\\dashboard\\static\\dashboard.js", "source_location": "L1384", "weight": 1.0}, {"source": "dashboard", "target": "dashboard_workflowdetail", "relation": "contains", "confidence": "EXTRACTED", "source_file": "packages\\flowwatch\\src\\dashboard\\static\\dashboard.js", "source_location": "L1396", "weight": 1.0}, {"source": "dashboard", "target": "dashboard_executiondetail", "relation": "contains", "confidence": "EXTRACTED", "source_file": "packages\\flowwatch\\src\\dashboard\\static\\dashboard.js", "source_location": "L1460", "weight": 1.0}, {"source": "dashboard", "target": "dashboard_errordetail", "relation": "contains", "confidence": "EXTRACTED", "source_file": "packages\\flowwatch\\src\\dashboard\\static\\dashboard.js", "source_location": "L1501", "weight": 1.0}, {"source": "dashboard", "target": "dashboard_tracedetail", "relation": "contains", "confidence": "EXTRACTED", "source_file": "packages\\flowwatch\\src\\dashboard\\static\\dashboard.js", "source_location": "L1517", "weight": 1.0}, {"source": "dashboard", "target": "dashboard_syncui", "relation": "contains", "confidence": "EXTRACTED", "source_file": "packages\\flowwatch\\src\\dashboard\\static\\dashboard.js", "source_location": "L1852", "weight": 1.0}, {"source": "dashboard_apipath", "target": "dashboard_dashboardbasepath", "relation": "calls", "confidence": "EXTRACTED", "source_file": "packages\\flowwatch\\src\\dashboard\\static\\dashboard.js", "source_location": "L74", "weight": 1.0}, {"source": "dashboard_apirequest", "target": "dashboard_apipath", "relation": "calls", "confidence": "EXTRACTED", "source_file": "packages\\flowwatch\\src\\dashboard\\static\\dashboard.js", "source_location": "L87", "weight": 1.0}, {"source": "dashboard_normalizeworkflow", "target": "dashboard_pinnedworkflownames", "relation": "calls", "confidence": "EXTRACTED", "source_file": "packages\\flowwatch\\src\\dashboard\\static\\dashboard.js", "source_location": "L122", "weight": 1.0}, {"source": "dashboard_normalizeworkflow", "target": "dashboard_formatdatetime", "relation": "calls", "confidence": "EXTRACTED", "source_file": "packages\\flowwatch\\src\\dashboard\\static\\dashboard.js", "source_location": "L132", "weight": 1.0}, {"source": "dashboard_normalizeexecution", "target": "dashboard_formattime", "relation": "calls", "confidence": "EXTRACTED", "source_file": "packages\\flowwatch\\src\\dashboard\\static\\dashboard.js", "source_location": "L145", "weight": 1.0}, {"source": "dashboard_normalizeexecution", "target": "dashboard_formatdurationlabel", "relation": "calls", "confidence": "EXTRACTED", "source_file": "packages\\flowwatch\\src\\dashboard\\static\\dashboard.js", "source_location": "L149", "weight": 1.0}, {"source": "dashboard_normalizeerror", "target": "dashboard_formattime", "relation": "calls", "confidence": "EXTRACTED", "source_file": "packages\\flowwatch\\src\\dashboard\\static\\dashboard.js", "source_location": "L169", "weight": 1.0}, {"source": "dashboard_loaddashboarddata", "target": "dashboard_apirequest", "relation": "calls", "confidence": "EXTRACTED", "source_file": "packages\\flowwatch\\src\\dashboard\\static\\dashboard.js", "source_location": "L204", "weight": 1.0}, {"source": "dashboard_loaddashboarddata", "target": "dashboard_renderall", "relation": "calls", "confidence": "EXTRACTED", "source_file": "packages\\flowwatch\\src\\dashboard\\static\\dashboard.js", "source_location": "L232", "weight": 1.0}, {"source": "dashboard_badgeforstatus", "target": "dashboard_escapehtml", "relation": "calls", "confidence": "EXTRACTED", "source_file": "packages\\flowwatch\\src\\dashboard\\static\\dashboard.js", "source_location": "L236", "weight": 1.0}, {"source": "dashboard_tableemptyrow", "target": "dashboard_escapehtml", "relation": "calls", "confidence": "EXTRACTED", "source_file": "packages\\flowwatch\\src\\dashboard\\static\\dashboard.js", "source_location": "L254", "weight": 1.0}, {"source": "dashboard_badgeformethod", "target": "dashboard_escapehtml", "relation": "calls", "confidence": "EXTRACTED", "source_file": "packages\\flowwatch\\src\\dashboard\\static\\dashboard.js", "source_location": "L275", "weight": 1.0}, {"source": "dashboard_showpage", "target": "dashboard_closedrawer", "relation": "calls", "confidence": "EXTRACTED", "source_file": "packages\\flowwatch\\src\\dashboard\\static\\dashboard.js", "source_location": "L285", "weight": 1.0}, {"source": "dashboard_showpage", "target": "dashboard_loadaiinsights", "relation": "calls", "confidence": "EXTRACTED", "source_file": "packages\\flowwatch\\src\\dashboard\\static\\dashboard.js", "source_location": "L288", "weight": 1.0}, {"source": "dashboard_showpage", "target": "dashboard_initaichat", "relation": "calls", "confidence": "EXTRACTED", "source_file": "packages\\flowwatch\\src\\dashboard\\static\\dashboard.js", "source_location": "L291", "weight": 1.0}, {"source": "dashboard_showpage", "target": "dashboard_loadgroqmodelsforsettings", "relation": "calls", "confidence": "EXTRACTED", "source_file": "packages\\flowwatch\\src\\dashboard\\static\\dashboard.js", "source_location": "L294", "weight": 1.0}, {"source": "dashboard_workflowerrorforstep", "target": "dashboard_latestexecutionforworkflow", "relation": "calls", "confidence": "EXTRACTED", "source_file": "packages\\flowwatch\\src\\dashboard\\static\\dashboard.js", "source_location": "L322", "weight": 1.0}, {"source": "dashboard_badgeforstepstatus", "target": "dashboard_badgeforstatus", "relation": "calls", "confidence": "EXTRACTED", "source_file": "packages\\flowwatch\\src\\dashboard\\static\\dashboard.js", "source_location": "L384", "weight": 1.0}, {"source": "dashboard_badgeforstepstatus", "target": "dashboard_escapehtml", "relation": "calls", "confidence": "EXTRACTED", "source_file": "packages\\flowwatch\\src\\dashboard\\static\\dashboard.js", "source_location": "L385", "weight": 1.0}, {"source": "dashboard_workflowsteperrordetail", "target": "dashboard_escapehtml", "relation": "calls", "confidence": "EXTRACTED", "source_file": "packages\\flowwatch\\src\\dashboard\\static\\dashboard.js", "source_location": "L392", "weight": 1.0}, {"source": "dashboard_renderoverview", "target": "dashboard_tableemptyrow", "relation": "calls", "confidence": "EXTRACTED", "source_file": "packages\\flowwatch\\src\\dashboard\\static\\dashboard.js", "source_location": "L464", "weight": 1.0}, {"source": "dashboard_renderoverview", "target": "dashboard_escapehtml", "relation": "calls", "confidence": "EXTRACTED", "source_file": "packages\\flowwatch\\src\\dashboard\\static\\dashboard.js", "source_location": "L490", "weight": 1.0}, {"source": "dashboard_renderworkflows", "target": "dashboard_escapehtml", "relation": "calls", "confidence": "EXTRACTED", "source_file": "packages\\flowwatch\\src\\dashboard\\static\\dashboard.js", "source_location": "L518", "weight": 1.0}, {"source": "dashboard_renderworkflows", "target": "dashboard_tableemptyrow", "relation": "calls", "confidence": "EXTRACTED", "source_file": "packages\\flowwatch\\src\\dashboard\\static\\dashboard.js", "source_location": "L533", "weight": 1.0}, {"source": "dashboard_getworkflowstepclass", "target": "dashboard_latestexecutionforworkflow", "relation": "calls", "confidence": "EXTRACTED", "source_file": "packages\\flowwatch\\src\\dashboard\\static\\dashboard.js", "source_location": "L537", "weight": 1.0}, {"source": "dashboard_getworkflowstepclass", "target": "dashboard_workflowstepstatus", "relation": "calls", "confidence": "EXTRACTED", "source_file": "packages\\flowwatch\\src\\dashboard\\static\\dashboard.js", "source_location": "L538", "weight": 1.0}, {"source": "dashboard_getworkflowarrowclass", "target": "dashboard_latestexecutionforworkflow", "relation": "calls", "confidence": "EXTRACTED", "source_file": "packages\\flowwatch\\src\\dashboard\\static\\dashboard.js", "source_location": "L546", "weight": 1.0}, {"source": "dashboard_getworkflowarrowclass", "target": "dashboard_workflowstepstatus", "relation": "calls", "confidence": "EXTRACTED", "source_file": "packages\\flowwatch\\src\\dashboard\\static\\dashboard.js", "source_location": "L547", "weight": 1.0}, {"source": "dashboard_renderexecutions", "target": "dashboard_tableemptyrow", "relation": "calls", "confidence": "EXTRACTED", "source_file": "packages\\flowwatch\\src\\dashboard\\static\\dashboard.js", "source_location": "L573", "weight": 1.0}, {"source": "dashboard_renderflags", "target": "dashboard_tableemptyrow", "relation": "calls", "confidence": "EXTRACTED", "source_file": "packages\\flowwatch\\src\\dashboard\\static\\dashboard.js", "source_location": "L589", "weight": 1.0}, {"source": "dashboard_rendererrors", "target": "dashboard_tableemptyrow", "relation": "calls", "confidence": "EXTRACTED", "source_file": "packages\\flowwatch\\src\\dashboard\\static\\dashboard.js", "source_location": "L612", "weight": 1.0}, {"source": "dashboard_rendertraces", "target": "dashboard_tableemptyrow", "relation": "calls", "confidence": "EXTRACTED", "source_file": "packages\\flowwatch\\src\\dashboard\\static\\dashboard.js", "source_location": "L634", "weight": 1.0}, {"source": "dashboard_rendertraces", "target": "dashboard_rendertracegraph", "relation": "calls", "confidence": "EXTRACTED", "source_file": "packages\\flowwatch\\src\\dashboard\\static\\dashboard.js", "source_location": "L639", "weight": 1.0}, {"source": "dashboard_rendertracegraph", "target": "dashboard_escapehtml", "relation": "calls", "confidence": "EXTRACTED", "source_file": "packages\\flowwatch\\src\\dashboard\\static\\dashboard.js", "source_location": "L738", "weight": 1.0}, {"source": "dashboard_rendertracegraph", "target": "dashboard_formattime", "relation": "calls", "confidence": "EXTRACTED", "source_file": "packages\\flowwatch\\src\\dashboard\\static\\dashboard.js", "source_location": "L763", "weight": 1.0}, {"source": "dashboard_renderglobalsearch", "target": "dashboard_escapehtml", "relation": "calls", "confidence": "EXTRACTED", "source_file": "packages\\flowwatch\\src\\dashboard\\static\\dashboard.js", "source_location": "L862", "weight": 1.0}, {"source": "dashboard_renderhealth", "target": "dashboard_badgeforstatus", "relation": "calls", "confidence": "EXTRACTED", "source_file": "packages\\flowwatch\\src\\dashboard\\static\\dashboard.js", "source_location": "L873", "weight": 1.0}, {"source": "dashboard_renderhealth", "target": "dashboard_escapehtml", "relation": "calls", "confidence": "EXTRACTED", "source_file": "packages\\flowwatch\\src\\dashboard\\static\\dashboard.js", "source_location": "L896", "weight": 1.0}, {"source": "dashboard_rendersettings", "target": "dashboard_rendergroqmodelcontrols", "relation": "calls", "confidence": "EXTRACTED", "source_file": "packages\\flowwatch\\src\\dashboard\\static\\dashboard.js", "source_location": "L929", "weight": 1.0}, {"source": "dashboard_savesetting", "target": "dashboard_apirequest", "relation": "calls", "confidence": "EXTRACTED", "source_file": "packages\\flowwatch\\src\\dashboard\\static\\dashboard.js", "source_location": "L940", "weight": 1.0}, {"source": "dashboard_savesetting", "target": "dashboard_rendersettings", "relation": "calls", "confidence": "EXTRACTED", "source_file": "packages\\flowwatch\\src\\dashboard\\static\\dashboard.js", "source_location": "L947", "weight": 1.0}, {"source": "dashboard_togglesetting", "target": "dashboard_apirequest", "relation": "calls", "confidence": "EXTRACTED", "source_file": "packages\\flowwatch\\src\\dashboard\\static\\dashboard.js", "source_location": "L973", "weight": 1.0}, {"source": "dashboard_togglesetting", "target": "dashboard_rendersettings", "relation": "calls", "confidence": "EXTRACTED", "source_file": "packages\\flowwatch\\src\\dashboard\\static\\dashboard.js", "source_location": "L980", "weight": 1.0}, {"source": "dashboard_savegroqapikey", "target": "dashboard_apirequest", "relation": "calls", "confidence": "EXTRACTED", "source_file": "packages\\flowwatch\\src\\dashboard\\static\\dashboard.js", "source_location": "L1006", "weight": 1.0}, {"source": "dashboard_groqmodeloptions", "target": "dashboard_selectedgroqmodel", "relation": "calls", "confidence": "EXTRACTED", "source_file": "packages\\flowwatch\\src\\dashboard\\static\\dashboard.js", "source_location": "L1051", "weight": 1.0}, {"source": "dashboard_rendergroqmodelcontrols", "target": "dashboard_selectedgroqmodel", "relation": "calls", "confidence": "EXTRACTED", "source_file": "packages\\flowwatch\\src\\dashboard\\static\\dashboard.js", "source_location": "L1059", "weight": 1.0}, {"source": "dashboard_rendergroqmodelcontrols", "target": "dashboard_groqmodeloptions", "relation": "calls", "confidence": "EXTRACTED", "source_file": "packages\\flowwatch\\src\\dashboard\\static\\dashboard.js", "source_location": "L1060", "weight": 1.0}, {"source": "dashboard_loadaiinsights", "target": "dashboard_renderaiplaceholders", "relation": "calls", "confidence": "EXTRACTED", "source_file": "packages\\flowwatch\\src\\dashboard\\static\\dashboard.js", "source_location": "L1155", "weight": 1.0}, {"source": "dashboard_loadaiinsights", "target": "dashboard_apirequest", "relation": "calls", "confidence": "EXTRACTED", "source_file": "packages\\flowwatch\\src\\dashboard\\static\\dashboard.js", "source_location": "L1158", "weight": 1.0}, {"source": "dashboard_loadgroqmodelsforsettings", "target": "dashboard_apipath", "relation": "calls", "confidence": "EXTRACTED", "source_file": "packages\\flowwatch\\src\\dashboard\\static\\dashboard.js", "source_location": "L1177", "weight": 1.0}, {"source": "dashboard_loadgroqmodelsforsettings", "target": "dashboard_rendergroqmodelcontrols", "relation": "calls", "confidence": "EXTRACTED", "source_file": "packages\\flowwatch\\src\\dashboard\\static\\dashboard.js", "source_location": "L1182", "weight": 1.0}, {"source": "dashboard_initaichat", "target": "dashboard_rendermessages", "relation": "calls", "confidence": "EXTRACTED", "source_file": "packages\\flowwatch\\src\\dashboard\\static\\dashboard.js", "source_location": "L1192", "weight": 1.0}, {"source": "dashboard_clearaichat", "target": "dashboard_savemessages", "relation": "calls", "confidence": "EXTRACTED", "source_file": "packages\\flowwatch\\src\\dashboard\\static\\dashboard.js", "source_location": "L1201", "weight": 1.0}, {"source": "dashboard_clearaichat", "target": "dashboard_rendermessages", "relation": "calls", "confidence": "EXTRACTED", "source_file": "packages\\flowwatch\\src\\dashboard\\static\\dashboard.js", "source_location": "L1202", "weight": 1.0}, {"source": "dashboard_sendmessage", "target": "dashboard_savemessages", "relation": "calls", "confidence": "EXTRACTED", "source_file": "packages\\flowwatch\\src\\dashboard\\static\\dashboard.js", "source_location": "L1339", "weight": 1.0}, {"source": "dashboard_sendmessage", "target": "dashboard_rendermessages", "relation": "calls", "confidence": "EXTRACTED", "source_file": "packages\\flowwatch\\src\\dashboard\\static\\dashboard.js", "source_location": "L1340", "weight": 1.0}, {"source": "dashboard_sendmessage", "target": "dashboard_apipath", "relation": "calls", "confidence": "EXTRACTED", "source_file": "packages\\flowwatch\\src\\dashboard\\static\\dashboard.js", "source_location": "L1355", "weight": 1.0}, {"source": "dashboard_renderall", "target": "dashboard_renderoverview", "relation": "calls", "confidence": "EXTRACTED", "source_file": "packages\\flowwatch\\src\\dashboard\\static\\dashboard.js", "source_location": "L1385", "weight": 1.0}, {"source": "dashboard_renderall", "target": "dashboard_renderworkflows", "relation": "calls", "confidence": "EXTRACTED", "source_file": "packages\\flowwatch\\src\\dashboard\\static\\dashboard.js", "source_location": "L1386", "weight": 1.0}, {"source": "dashboard_renderall", "target": "dashboard_renderexecutions", "relation": "calls", "confidence": "EXTRACTED", "source_file": "packages\\flowwatch\\src\\dashboard\\static\\dashboard.js", "source_location": "L1387", "weight": 1.0}, {"source": "dashboard_renderall", "target": "dashboard_renderflags", "relation": "calls", "confidence": "EXTRACTED", "source_file": "packages\\flowwatch\\src\\dashboard\\static\\dashboard.js", "source_location": "L1388", "weight": 1.0}, {"source": "dashboard_renderall", "target": "dashboard_rendererrors", "relation": "calls", "confidence": "EXTRACTED", "source_file": "packages\\flowwatch\\src\\dashboard\\static\\dashboard.js", "source_location": "L1389", "weight": 1.0}, {"source": "dashboard_renderall", "target": "dashboard_rendertraces", "relation": "calls", "confidence": "EXTRACTED", "source_file": "packages\\flowwatch\\src\\dashboard\\static\\dashboard.js", "source_location": "L1390", "weight": 1.0}, {"source": "dashboard_renderall", "target": "dashboard_renderhealth", "relation": "calls", "confidence": "EXTRACTED", "source_file": "packages\\flowwatch\\src\\dashboard\\static\\dashboard.js", "source_location": "L1391", "weight": 1.0}, {"source": "dashboard_renderall", "target": "dashboard_rendersettings", "relation": "calls", "confidence": "EXTRACTED", "source_file": "packages\\flowwatch\\src\\dashboard\\static\\dashboard.js", "source_location": "L1392", "weight": 1.0}, {"source": "dashboard_renderall", "target": "dashboard_renderaiplaceholders", "relation": "calls", "confidence": "EXTRACTED", "source_file": "packages\\flowwatch\\src\\dashboard\\static\\dashboard.js", "source_location": "L1393", "weight": 1.0}, {"source": "dashboard_workflowdetail", "target": "dashboard_latestexecutionforworkflow", "relation": "calls", "confidence": "EXTRACTED", "source_file": "packages\\flowwatch\\src\\dashboard\\static\\dashboard.js", "source_location": "L1397", "weight": 1.0}, {"source": "dashboard_workflowdetail", "target": "dashboard_allexecutionsforworkflow", "relation": "calls", "confidence": "EXTRACTED", "source_file": "packages\\flowwatch\\src\\dashboard\\static\\dashboard.js", "source_location": "L1398", "weight": 1.0}, {"source": "dashboard_workflowdetail", "target": "dashboard_workflowexecutionsteps", "relation": "calls", "confidence": "EXTRACTED", "source_file": "packages\\flowwatch\\src\\dashboard\\static\\dashboard.js", "source_location": "L1399", "weight": 1.0}, {"source": "dashboard_workflowdetail", "target": "dashboard_escapehtml", "relation": "calls", "confidence": "EXTRACTED", "source_file": "packages\\flowwatch\\src\\dashboard\\static\\dashboard.js", "source_location": "L1418", "weight": 1.0}, {"source": "dashboard_executiondetail", "target": "dashboard_workflowexecutionsteps", "relation": "calls", "confidence": "EXTRACTED", "source_file": "packages\\flowwatch\\src\\dashboard\\static\\dashboard.js", "source_location": "L1467", "weight": 1.0}, {"source": "dashboard_executiondetail", "target": "dashboard_escapehtml", "relation": "calls", "confidence": "EXTRACTED", "source_file": "packages\\flowwatch\\src\\dashboard\\static\\dashboard.js", "source_location": "L1471", "weight": 1.0}, {"source": "dashboard_executiondetail", "target": "dashboard_badgeforstatus", "relation": "calls", "confidence": "EXTRACTED", "source_file": "packages\\flowwatch\\src\\dashboard\\static\\dashboard.js", "source_location": "L1472", "weight": 1.0}, {"source": "dashboard_errordetail", "target": "dashboard_escapehtml", "relation": "calls", "confidence": "EXTRACTED", "source_file": "packages\\flowwatch\\src\\dashboard\\static\\dashboard.js", "source_location": "L1504", "weight": 1.0}, {"source": "dashboard_tracedetail", "target": "dashboard_escapehtml", "relation": "calls", "confidence": "EXTRACTED", "source_file": "packages\\flowwatch\\src\\dashboard\\static\\dashboard.js", "source_location": "L1522", "weight": 1.0}]}